arrc/__about__.py
arrc/__init__.py
arrc/ops.py
arrc/callbacks/__init__.py
arrc/callbacks/histogram_visualizer.py
arrc/callbacks/tsne_visualizer_callback.py
arrc/callbacks/umap_visualizer_callback.py
arrc/callbacks/visualizer_callback.py
arrc/layers/__init__.py
arrc/layers/additive_noise.py
arrc/layers/amp_scaling.py
arrc/layers/arc_face.py
arrc/layers/attention_pool_1d.py
arrc/layers/gated_convolution.py
arrc/layers/l2_normalization.py
arrc/layers/metric_embedding.py
arrc/layers/nan_check_layer.py
arrc/layers/rescale_layer.py
arrc/layers/time_shift.py
arrc/losses/__init__.py
arrc/losses/arc_face_loss.py
arrc/losses/center_loss.py
arrc/losses/combined_loss.py
arrc/losses/contrastive_loss.py
arrc/losses/distance_loss.py
arrc/losses/loss_wrapper.py
arrc/losses/triplet_loss.py
arrc/metrics/__init__.py
arrc/metrics/center_distance_metrics.py
arrc/metrics/mean_interclass_distance.py
arrc/metrics/mean_intraclass_distance.py
arrc/metrics/pairwise_distance_metric.py
arrc/models/__init__.py
arrc/models/aer_model.py
arrc/models/backends/__init__.py
arrc/models/backends/tensorflow.py
arrc/models/backends/torch.py
arrc/models/embeddings/__init__.py
arrc/models/embeddings/baseline.py
arrc/models/embeddings/bayesian_cnn_lstm.py
arrc/models/embeddings/cnn_wavenet.py
arrc/models/embeddings/embedding_utils.py
arrc/models/embeddings/petsfcnn.py
arrc/models/embeddings/resnet.py
arrc/models/embeddings/simple_cnn.py
arrc/models/embeddings/tcnn.py
arrc-0.6.1.1.dist-info/METADATA
arrc-0.6.1.1.dist-info/WHEEL
arrc-0.6.1.1.dist-info/licenses/LICENSE.txt
arrc-0.6.1.1.dist-info/RECORD
