Metadata-Version: 2.4
Name: arrc
Version: 0.6.1.1
Summary: Affective Research on Representations and Classifications (ARRC)
Project-URL: Documentation, https://affects.ai/arrc
Project-URL: Issues, https://github.com/Tim Sweeney-Fanelli/arrc/issues
Project-URL: Source, https://github.com/Tim Sweeney-Fanelli/arrc
Author-email: Tim Sweeney-Fanelli <tim@affects.ai>
License-Expression: MIT
License-File: LICENSE.txt
Classifier: Development Status :: 4 - Beta
Classifier: Programming Language :: Python
Classifier: Programming Language :: Python :: 3.8
Classifier: Programming Language :: Python :: 3.9
Classifier: Programming Language :: Python :: 3.10
Classifier: Programming Language :: Python :: 3.11
Classifier: Programming Language :: Python :: 3.12
Classifier: Programming Language :: Python :: Implementation :: CPython
Classifier: Programming Language :: Python :: Implementation :: PyPy
Requires-Python: >=3.8
Requires-Dist: hatch>=1.14.0
Requires-Dist: keras>=3.8.0
Requires-Dist: tensorflow>=2.17.0
Requires-Dist: umap-learn>=0.5.7
